{"wikiId": "28070112", "titre": "Oranges and Sunshine", "dateSortie": "2010-10-08", "duree": "", "genre": ["Drama"], "resume": "The film tells the story of Margaret Humphreys, a social worker from Nottingham who uncovered the scandal of \"home children\", Margaret reunites estranged families and brings worldwide attention to the cause. Deported children were promised oranges and sunshine but they got hard labour and life in institutions such as Keaney College in Bindoon, Western Australia.http://www.cacbindoon.wa.edu.au/history.html\n"}