{"wikiId": "1124048", "titre": "Taxi 2", "dateSortie": "2000-03-29", "duree": "82.0", "genre": ["Thriller", "Crime Fiction", "Parkour in popular culture", "Buddy film", "World cinema", "Chase Movie", "Action/Adventure", "Comedy", "Crime Thriller", "Action Thrillers", "Action"], "resume": "Taxi 2 tells the story of a Japanese minister of defence visiting Marseille to view the city police's anti-gang tactics. During the visit, however, he is kidnapped by a group working for the Japanese yakuza. Young officer Emilien  is determined to rescue the minister and officer Petra  , who was also kidnapped, and restore the honour of his department. Once again, speed demon taxi-driver Daniel  is called upon to save the day with his high-speed driving skills.\n"}