{"wikiId": "12561211", "titre": "Fate Is the Hunter", "dateSortie": "1964", "duree": "106.0", "genre": ["Disaster", "Action", "Drama", "Black-and-white"], "resume": "Pilot Jack Savage  is suspected of drinking and causing an airliner crash that kills 53 people and leaves only a single survivor, Martha Webster , a flight attendant. The captain's wartime buddy, airline executive Sam C. McBane , is convinced of his friend's innocence and investigates doggedly. Flashbacks deal with both Jack's past and Sam meeting him, plus others they used to know. Eventually, a test flight recreating the actual ill-fated flight shows that the crash was caused by a series of events.\n"}