{"wikiId": "1802864", "titre": "According to Spencer", "dateSortie": "2001", "duree": "94.0", "genre": ["Romantic comedy", "Romance Film", "Coming of age", "Indie", "Comedy"], "resume": "The film is centered on Spencer , who moves to Los Angeles and  runs into Melora , the girl he's been in love with since he was a child. Spencer is plagued by many obstacles in his new life: winning the girl of his dreams, finding success in his new job, and dealing with his two ambiguously-oriented roommates , who are obsessed with making a pornographic film and submitting it to what they believe is a contest.\n"}