{"wikiId": "23437747", "titre": "Madame Aema 10", "dateSortie": "1994-06-04", "duree": "102.0", "genre": ["Erotica"], "resume": "This time in the Madame Aema series, Aema leaves her husband, tired of his demanding ways. She moves to Jeju Island and lives with her friend, Young-ju. She begins having an affair with a member of a Samul nori group. Shocked by Young-ju's lesbian advances, and persuaded by her boyfriend, Aema returns to her husband.<ref namehttp://www.kmdb.or.kr/eng/md_basic.asp?nation04710|title2009-06-29|publisherKMDb Korean Movie Database}}\n"}