{"wikiId": "708870", "titre": "Don Juan DeMarco", "dateSortie": "1995-04-07", "duree": "92.0", "genre": ["Romantic comedy", "Comedy of manners", "Comedy-drama", "Drama", "Comedy", "Romantic drama", "Romance Film"], "resume": "Psychiatrist Jack Mickler  dissuades a would-be suicide\u2014a 21-year-old, costumed like Zorro and claiming to be Don Juan , who is then held for a ten-day review in a mental institution. Mickler, who is about to retire, insists on doing the evaluation and conducts it without medicating the youth. \"Don Juan\" tells his story\u2014born in Mexico, the death of his father, a year in a harem, and finding true love  on a remote island. Listening enlivens Mickler's relationship with his own wife, Marilyn . As the ten days tick down and pressure mounts on Mickler to support the youth's indefinite confinement, finding reality within the romantic imagination becomes Jack's last professional challenge.\n"}