{"wikiId": "18500449", "titre": "Edward and Caroline", "dateSortie": "1951-04-06", "duree": "88.0", "genre": ["Comedy", "Black-and-white"], "resume": "\u00c9douard and Caroline are preparing for a family evening during which \u00c9douard will be expected to play the piano. Lacking a dinner jacket \u00c9douard goes to borrow one from his wife's cousin. In the meantime Caroline attempts to re-model her dress to bring it more up-to-date. Her husband is not pleased and the evening consists of rows, fights and threats of divorce. It is the early morning before life returns to normal.\n"}