{"wikiId": "30972924", "titre": "The Circuit", "dateSortie": "2002", "duree": "91.0", "genre": ["Thriller", "Crime Fiction", "Action", "Martial Arts Film", "Action/Adventure"], "resume": "Years ago, Dirk Longstreet walked away from The Circuit, the merciless underground fight club with no rules, where money changes hands as men are killed. But now gangsters have got his brother, and only one more journey inside the ring will save his life. Or will it? Not without a fight.. Literally. And this time, it's personal.\n"}